uniparser_komi_zyrian/__init__.py
uniparser_komi_zyrian/data_nodiacritics/__init__.py
uniparser_komi_zyrian/data_nodiacritics/bad_analyses.txt
uniparser_komi_zyrian/data_nodiacritics/lex_rules.txt
uniparser_komi_zyrian/data_nodiacritics/lexemes.txt
uniparser_komi_zyrian/data_nodiacritics/paradigms.txt
uniparser_komi_zyrian/data_strict/__init__.py
uniparser_komi_zyrian/data_strict/bad_analyses.txt
uniparser_komi_zyrian/data_strict/lex_rules.txt
uniparser_komi_zyrian/data_strict/lexemes.txt
uniparser_komi_zyrian/data_strict/paradigms.txt
uniparser_komi_zyrian-1.1.21.dist-info/LICENSE
uniparser_komi_zyrian-1.1.21.dist-info/METADATA
uniparser_komi_zyrian-1.1.21.dist-info/WHEEL
uniparser_komi_zyrian-1.1.21.dist-info/top_level.txt
uniparser_komi_zyrian-1.1.21.dist-info/RECORD
